namepattern/__init__.py
namepattern/namepattern.py
namepattern-0.0.21.dist-info/LICENSE
namepattern-0.0.21.dist-info/METADATA
namepattern-0.0.21.dist-info/WHEEL
namepattern-0.0.21.dist-info/top_level.txt
namepattern-0.0.21.dist-info/RECORD
