Metadata-Version: 2.1
Name: namepattern
Version: 0.0.21
Summary: Printing name pattern with python
Home-page: UNKNOWN
Author: Arijit Ghosh
Author-email: subhasghosh196@gmail.com
License: UNKNOWN
Keywords: python,namepattern,pattern
Platform: UNKNOWN
Classifier: Development Status :: 1 - Planning
Classifier: Intended Audience :: Developers
Classifier: Programming Language :: Python :: 3
Classifier: Operating System :: Unix
Classifier: Operating System :: MacOS :: MacOS X
Classifier: Operating System :: Microsoft :: Windows
License-File: LICENSE
